snoo/__init__.py
snoo/client.py
snoo-0.3.1.dist-info/entry_points.txt
snoo-0.3.1.dist-info/LICENSE
snoo-0.3.1.dist-info/WHEEL
snoo-0.3.1.dist-info/METADATA
snoo-0.3.1.dist-info/RECORD
