Metadata-Version: 2.1
Name: snoo
Version: 0.3.1
Summary: Wrapper around the (undocumented) SNOO Smart Bassinet API
Home-page: https://github.com/maebert/snoo
License: MIT
Author: Manuel Ebert
Author-email: manuel@1450.me
Requires-Python: >=3.6,<4.0
Classifier: License :: OSI Approved :: MIT License
Classifier: Programming Language :: Python :: 3
Classifier: Programming Language :: Python :: 3.6
Classifier: Programming Language :: Python :: 3.7
Classifier: Programming Language :: Python :: 3.8
Requires-Dist: arrow (>=0.15.4,<0.16.0)
Requires-Dist: pyxdg (>=0.26,<0.27)
Requires-Dist: requests (>=2.22.0,<3.0.0)
Project-URL: Repository, https://github.com/maebert/snoo
